AUTHORS
CHANGES.rst
LICENSE
MANIFEST.in
README.rst
setup.cfg
setup.py
batemaneq/__init__.py
batemaneq/_bateman_double.cpp
batemaneq/_bateman_double.pyx
batemaneq/_release.py
batemaneq/bateman.py
batemaneq.egg-info/PKG-INFO
batemaneq.egg-info/SOURCES.txt
batemaneq.egg-info/dependency_links.txt
batemaneq.egg-info/not-zip-safe
batemaneq.egg-info/requires.txt
batemaneq.egg-info/top_level.txt
batemaneq/tests/__init__.py
batemaneq/tests/test_bateman.py
include/bateman.hpp
include/bateman_double.h
src/bateman_double.cpp