Metadata-Version: 1.1
Name: batemaneq
Version: 0.2.2
Summary: batemaneq provides a Python package for evaluating the Bateman equation
Home-page: https://github.com/bjodah/batemaneq
Author: Björn Dahlgren
Author-email: bjodah@DELETEMEgmail.com
License: BSD
Platform: UNKNOWN
Classifier: Development Status :: 4 - Beta
Classifier: License :: OSI Approved :: BSD License
Classifier: Operating System :: OS Independent
Classifier: Topic :: Scientific/Engineering
Classifier: Topic :: Scientific/Engineering :: Mathematics
